README.txt
setup.cfg
setup.py
AdjectorClient.egg-info/PKG-INFO
AdjectorClient.egg-info/SOURCES.txt
AdjectorClient.egg-info/dependency_links.txt
AdjectorClient.egg-info/namespace_packages.txt
AdjectorClient.egg-info/requires.txt
AdjectorClient.egg-info/top_level.txt
adjector/__init__.py
adjector/client/__init__.py
adjector/client/client.py
adjector/core/__init__.py
adjector/core/cj_util.py
adjector/core/conf.py
adjector/core/render.py
adjector/core/tracking.py
adjector/core/contrib/__init__.py
adjector/core/contrib/converters.py
adjector/model/__init__.py
adjector/model/entities.py
adjector/model/meta.py