Metadata-Version: 1.0
Name: AdjectorClient
Version: 1.0b2
Summary: Client-only package for Adjector, a lightweight, fast, flexible ad server.
Home-page: http://projects.icapsid.net/adjector
Author: David Isaacson
Author-email: david@icapsid.net
License: GPL v2 or v3 (at your option)
Platform: UNKNOWN
